[
  {
    "ID": 454492255932252160,
    "roses": 2,
    "plrroses": 3,
    "points": 1078
  },
  {
    "ID": 457956885748908034,
    "roses": 0,
    "plrroses": 0,
    "points": 472
  },
  {
    "ID": 347270552291115008,
    "roses": 0,
    "plrroses": 1,
    "points": 589
  },
  {
    "ID": 531662657690927105,
    "roses": 0,
    "plrroses": 5,
    "points": 244
  },
  {
    "ID": 523140055125196800,
    "roses": 0,
    "plrroses": 17,
    "points": 313
  },
  {
    "ID": 286089091303342080,
    "roses": 0,
    "plrroses": 0,
    "points": 292
  },
  {
    "ID": 553560889073336360,
    "roses": 0,
    "plrroses": 0,
    "points": 178
  },
  {
    "ID": 527753511199571968,
    "roses": 0,
    "plrroses": 0,
    "points": 20
  },
  {
    "ID": 559062523169734656,
    "roses": 0,
    "plrroses": 4,
    "points": 827
  },
  {
    "ID": 580596443581251605,
    "roses": 0,
    "plrroses": 3,
    "points": 797
  },
  {
    "ID": 576978587983282177,
    "roses": 0,
    "plrroses": 0,
    "points": 55
  },
  {
    "ID": 558293522743296001,
    "roses": 0,
    "plrroses": 0,
    "points": 0
  },
  {
    "ID": 582510114473246720,
    "roses": 0,
    "plrroses": 0,
    "points": 42
  },
  {
    "ID": 582503548596781056,
    "roses": 0,
    "plrroses": 0,
    "points": 606
  },
  {
    "ID": 548704942353809409,
    "roses": 0,
    "plrroses": 0,
    "points": 0
  },
  {
    "ID": 469340067207315457,
    "roses": 2,
    "plrroses": 6,
    "points": 4292
  },
  {
    "ID": 477652987758641153,
    "roses": 0,
    "plrroses": 0,
    "points": 66
  },
  {
    "ID": 581646149333549065,
    "roses": 1,
    "plrroses": 0,
    "points": 192
  },
  {
    "ID": 545626357741256715,
    "roses": 0,
    "plrroses": 0,
    "points": 22
  },
  {
    "ID": 583834635675631616,
    "roses": 0,
    "plrroses": 0,
    "points": 10
  },
  {
    "ID": 477423685330796601,
    "roses": 0,
    "plrroses": 0,
    "points": 146
  },
  {
    "ID": 308593628086009858,
    "roses": 0,
    "plrroses": 0,
    "points": 72
  },
  {
    "ID": 529601772675661835,
    "roses": 0,
    "plrroses": 1,
    "points": 135
  },
  {
    "ID": 429869027511500810,
    "roses": 0,
    "plrroses": 0,
    "points": 76
  },
  {
    "ID": 438851750829490189,
    "roses": 1110014131123,
    "plrroses": 0,
    "points": 12
  },
  {
    "ID": 362434269332635648,
    "roses": 0,
    "plrroses": 0,
    "points": 0
  },
  {
    "ID": 537360909589413888,
    "roses": 0,
    "plrroses": 0,
    "points": 10
  },
  {
    "ID": 581842467549347840,
    "roses": 0,
    "plrroses": 0,
    "points": 10
  },
  {
    "ID": 410241071419752468,
    "roses": 0,
    "plrroses": 0,
    "points": 10
  },
  {
    "ID": 439431114545692673,
    "roses": 0,
    "plrroses": 0,
    "points": 10
  },
  {
    "ID": 452610610937593876,
    "roses": 0,
    "plrroses": 0,
    "points": 10
  },
  {
    "ID": 353899857938743297,
    "roses": 0,
    "plrroses": 0,
    "points": 10
  },
  {
    "ID": 215498607703490560,
    "roses": 0,
    "plrroses": 0,
    "points": 0
  },
  {
    "ID": 565417528604622850,
    "roses": 0,
    "plrroses": 0,
    "points": 30
  },
  {
    "ID": 558957352217346063,
    "roses": 0,
    "plrroses": 0,
    "points": 273
  },
  {
    "ID": 396711857282613250,
    "roses": 0,
    "plrroses": 0,
    "points": 15
  },
  {
    "ID": 583609766002032640,
    "roses": 0,
    "plrroses": 0,
    "points": 65
  },
  {
    "ID": 393095069051256832,
    "roses": 0,
    "plrroses": 0,
    "points": 217
  },
  {
    "ID": 583604578612805632,
    "roses": 0,
    "plrroses": 0,
    "points": 28
  },
  {
    "ID": 427037970428854282,
    "roses": 0,
    "plrroses": 0,
    "points": 22
  },
  {
    "ID": 504175372804423682,
    "roses": 0,
    "plrroses": 0,
    "points": 58
  },
  {
    "ID": 439411814606962688,
    "roses": 0,
    "plrroses": 0,
    "points": 0
  },
  {
    "ID": 445576165139283979,
    "roses": 0,
    "plrroses": 0,
    "points": 20
  },
  {
    "ID": 584885904783704064,
    "roses": 0,
    "plrroses": 1,
    "points": 664
  },
  {
    "ID": 584806643271860272,
    "roses": 0,
    "plrroses": 0,
    "points": 25
  },
  {
    "ID": 342897246867685377,
    "roses": 0,
    "plrroses": 4,
    "points": 1176
  },
  {
    "ID": 366549823316426753,
    "roses": 0,
    "plrroses": 0,
    "points": 32
  },
  {
    "ID": 580967471402582028,
    "roses": 0,
    "plrroses": 0,
    "points": 17
  },
  {
    "ID": 561566619265138728,
    "roses": 2,
    "plrroses": 0,
    "points": 169
  },
  {
    "ID": 430387686847676417,
    "roses": 0,
    "plrroses": 0,
    "points": 158
  },
  {
    "ID": 554983235545858050,
    "roses": 0,
    "plrroses": 1,
    "points": 621
  },
  {
    "ID": 554637831465861150,
    "roses": 2,
    "plrroses": 1,
    "points": 527
  },
  {
    "ID": 379977774825209858,
    "roses": 0,
    "plrroses": 0,
    "points": 59
  },
  {
    "ID": 326306397635477504,
    "roses": 1,
    "plrroses": 0,
    "points": 1
  },
  {
    "ID": 541914115182952449,
    "roses": 0,
    "plrroses": 0,
    "points": 10
  },
  {
    "ID": 396492419505586188,
    "roses": 0,
    "plrroses": 0,
    "points": 15
  },
  {
    "ID": 563706272600293382,
    "roses": 0,
    "plrroses": 0,
    "points": 0
  },
  {
    "ID": 570617068672647262,
    "roses": 0,
    "plrroses": 0,
    "points": 112
  },
  {
    "ID": 528238489846939649,
    "roses": 0,
    "plrroses": 0,
    "points": 59
  },
  {
    "ID": 569100562700828684,
    "roses": 0,
    "plrroses": 0,
    "points": 59
  },
  {
    "ID": 528231100430942228,
    "roses": 0,
    "plrroses": 0,
    "points": 33
  },
  {
    "ID": 437458623682183188,
    "roses": 0,
    "plrroses": 0,
    "points": 59
  },
  {
    "ID": 494119651035447306,
    "roses": 0,
    "plrroses": 0,
    "points": 52
  },
  {
    "ID": 457790421062647819,
    "roses": 0,
    "plrroses": 0,
    "points": 34
  },
  {
    "ID": 562303986766446622,
    "roses": 0,
    "plrroses": 0,
    "points": 16
  },
  {
    "ID": 586807900840656917,
    "roses": 0,
    "plrroses": 0,
    "points": 10
  },
  {
    "ID": 531494476544475167,
    "roses": 0,
    "plrroses": 0,
    "points": 242
  },
  {
    "ID": 572289024262144000,
    "roses": 0,
    "plrroses": 0,
    "points": 33
  },
  {
    "ID": 524885751129702420,
    "roses": 0,
    "plrroses": 0,
    "points": 26
  },
  {
    "ID": 514403347755958312,
    "roses": 0,
    "plrroses": 0,
    "points": 48
  },
  {
    "ID": 555026573602979865,
    "roses": 0,
    "plrroses": 0,
    "points": 305
  },
  {
    "ID": 555781567260131349,
    "roses": 0,
    "plrroses": 1,
    "points": 471
  },
  {
    "ID": 385750501536301057,
    "roses": 0,
    "plrroses": 0,
    "points": 91
  },
  {
    "ID": 543085282396864513,
    "roses": 0,
    "plrroses": 0,
    "points": 12
  },
  {
    "ID": 587514406930219058,
    "roses": 0,
    "plrroses": 0,
    "points": 96
  },
  {
    "ID": 392157988246519808,
    "roses": 0,
    "plrroses": 0,
    "points": 226
  },
  {
    "ID": 540077591638573057,
    "roses": 0,
    "plrroses": 0,
    "points": 12
  },
  {
    "ID": 587754425137758251,
    "roses": 0,
    "plrroses": 0,
    "points": 4
  },
  {
    "ID": 587860180310425600,
    "roses": 0,
    "plrroses": 5,
    "points": 1160
  },
  {
    "ID": 402991890116509698,
    "roses": 0,
    "plrroses": 0,
    "points": 110
  },
  {
    "ID": 565171761159864350,
    "roses": 0,
    "plrroses": 5,
    "points": 0
  },
  {
    "ID": 576768532570963978,
    "roses": 0,
    "plrroses": 0,
    "points": 22
  },
  {
    "ID": 299105606642696193,
    "roses": 0,
    "plrroses": 0,
    "points": 52
  },
  {
    "ID": 390019107363225602,
    "roses": 0,
    "plrroses": 0,
    "points": 8
  },
  {
    "ID": 588267736694784002,
    "roses": 0,
    "plrroses": 0,
    "points": 10
  },
  {
    "ID": 586101901502840833,
    "roses": 0,
    "plrroses": 0,
    "points": 22
  },
  {
    "ID": 588663866955661352,
    "roses": 0,
    "plrroses": 1,
    "points": 98
  },
  {
    "ID": 563705592947146773,
    "roses": 0,
    "plrroses": 0,
    "points": 28
  },
  {
    "ID": 588785893557403682,
    "roses": 0,
    "plrroses": 0,
    "points": 10
  },
  {
    "ID": 405960092601810945,
    "roses": 0,
    "plrroses": 0,
    "points": 355
  },
  {
    "ID": 572244140398477312,
    "roses": 0,
    "plrroses": 0,
    "points": 81
  },
  {
    "ID": 454195778676719637,
    "roses": 0,
    "plrroses": 0,
    "points": 209
  },
  {
    "ID": 455385177959563265,
    "roses": 0,
    "plrroses": 0,
    "points": 20
  },
  {
    "ID": 590031454659018752,
    "roses": 0,
    "plrroses": 0,
    "points": 10
  },
  {
    "ID": 590030652427206659,
    "roses": 0,
    "plrroses": 0,
    "points": 15
  },
  {
    "ID": 590162479926214696,
    "roses": 0,
    "plrroses": 0,
    "points": 22
  },
  {
    "ID": 494503232689668097,
    "roses": 0,
    "plrroses": 0,
    "points": 48
  },
  {
    "ID": 543809081752944640,
    "roses": 0,
    "plrroses": 0,
    "points": 141
  },
  {
    "ID": 496915901720035328,
    "roses": 0,
    "plrroses": 0,
    "points": 39
  },
  {
    "ID": 580315235748020234,
    "roses": 0,
    "plrroses": 0,
    "points": 42
  },
  {
    "ID": 590440328213823488,
    "roses": 0,
    "plrroses": 0,
    "points": 112
  },
  {
    "ID": 551013357470089228,
    "roses": 0,
    "plrroses": 0,
    "points": 14
  },
  {
    "ID": 527378452416823297,
    "roses": 0,
    "plrroses": 0,
    "points": 24
  },
  {
    "ID": 271498497763573760,
    "roses": 0,
    "plrroses": 0,
    "points": 12
  },
  {
    "ID": 550312895519522846,
    "roses": 0,
    "plrroses": 0,
    "points": 12
  },
  {
    "ID": 591072887558111257,
    "roses": 0,
    "plrroses": 0,
    "points": 75
  },
  {
    "ID": 590208155561230336,
    "roses": 0,
    "plrroses": 0,
    "points": 0
  },
  {
    "ID": 591630350472708126,
    "roses": 0,
    "plrroses": 0,
    "points": 64
  },
  {
    "ID": 591916069896323072,
    "roses": 0,
    "plrroses": 0,
    "points": 28
  },
  {
    "ID": 591988441714130977,
    "roses": 0,
    "plrroses": 0,
    "points": 16
  },
  {
    "ID": 572031847555399681,
    "roses": 0,
    "plrroses": 0,
    "points": 18
  }
]